BCRA_Wrapper/BCRA_Wrapper.py
BCRA_Wrapper/__init__.py
BCRA_Wrapper-0.0.1.dist-info/LICENSE
BCRA_Wrapper-0.0.1.dist-info/METADATA
BCRA_Wrapper-0.0.1.dist-info/WHEEL
BCRA_Wrapper-0.0.1.dist-info/top_level.txt
BCRA_Wrapper-0.0.1.dist-info/RECORD
